README.md
setup.cfg
setup.py
microservice/__init__.py
microservice/cfg.py
microservice/enum.py
microservice/exceptions.py
microservice/functions.py
microservice/metrics.py
microservice/models.py
microservice/routes.py
microservice/server.py
microservice/tools.py
microservice.egg-info/PKG-INFO
microservice.egg-info/SOURCES.txt
microservice.egg-info/dependency_links.txt
microservice.egg-info/requires.txt
microservice.egg-info/top_level.txt
microservice/handlers/__init__.py
microservice/handlers/container.py
microservice/handlers/handler.py
microservice/handlers/metrics.py
microservice/managers/__init__.py
microservice/managers/manager.py
microservice/managers/session.py
microservice/managers/social.py
microservice/managers/user.py
microservice/middleware/__init__.py
microservice/middleware/cache.py
microservice/middleware/objects.py
microservice/middleware/session.py
microservice/middleware/user.py
microservice/migrations/__init__.py
microservice/migrations/migration001_example.py